{
  "navItems": [
    {
      "name": "Home",
      "path": "/"
    },
    {
      "name": "Our Philosophy",
      "path": "/our-philosophy"
    },
    {
      "name": "Organic Ingredients",
      "dropdown": [
        {
          "name": "Sourdough Starter",
          "path": "/ingredients-sourdough-starter"
        },
        {
          "name": "Celtic Salt",
          "path": "/ingredients-celtic-salt"
        },
        {
          "name": "Organic Flour",
          "path": "/ingredients-organic-flour"
        },
        {
          "name": "Filtered Water",
          "path": "/ingredients-filtered-water"
        }
      ]
    },
    {
      "name": "FAQ",
      "path": "/faq"
    },
    {
      "name": "Gallery",
      "path": "/gallery"
    },
    {
      "name": "Contact Us",
      "path": "/contact-us"
    }
  ]
}
